copykitten-2.0.0.dist-info/METADATA
copykitten-2.0.0.dist-info/WHEEL
copykitten-2.0.0.dist-info/licenses/LICENSE
copykitten/__init__.py
copykitten/_copykitten.abi3.so
copykitten/_copykitten.pyi
copykitten/py.typed
copykitten-2.0.0.dist-info/RECORD
